{"cameraMode":{"drawMode":0,"name":"Shaded","section":"Shading Mode"},"sceneLighting":false,"audioPlay":false,"sceneViewState":{"m_AlwaysRefresh":false,"showFog":true,"showSkybox":false,"showFlares":true,"showImageEffects":true,"showParticleSystems":true,"showVisualEffectGraphs":true,"m_FxEnabled":true},"in2DMode":false,"pivot":{"x":-6.975203037261963,"y":-2.9979443550109865,"z":0.4729313552379608},"rotation":{"x":0.32216787338256838,"y":-0.29788318276405337,"z":0.1075218915939331,"w":0.8921998143196106},"size":10.0,"orthographic":false}